{
  "guidelines": {
    "CKV_SECRET_6": "https://docs.checkr.confluence/docs/git_secrets_6",
    "CKV_AWS_11": "https://docs.checkr.confluence/docs/iam_6",
    "CKV_AWS_12": "https://docs.checkr.confluence/docs/iam_8",
    "CKV_AWS_40": "https://docs.checkr.confluence/docs/iam_16-iam-policy-privileges-1",
    "CKV_SECRET_7": "https://docs.checkr.confluence/docs/git_secrets_7",
    "CKV_AWS_14": "https://docs.checkr.confluence/docs/iam_7",
    "CKV_AWS_49": "https://docs.checkr.confluence/docs/bc_aws_iam_43",
    "CKV_AWS_60": "https://docs.checkr.confluence/docs/bc_aws_iam_44",
    "CKV_AWS_61": "https://docs.checkr.confluence/docs/bc_aws_iam_45",
    "CKV_AWS_72": "https://docs.checkr.confluence/docs/bc_aws_iam_46",
    "CKV_AWS_67": "https://docs.checkr.confluence/docs/logging_1",
    "CKV_AWS_36": "https://docs.checkr.confluence/docs/logging_2",
    "CKV_AWS_65": "https://docs.checkr.confluence/docs/bc_aws_logging_11",
    "CKV_AWS_24": "https://docs.checkr.confluence/docs/networking_1-port-security",
    "CKV_AWS_25": "https://docs.checkr.confluence/docs/networking_2",
    "CKV2_AWS_12": "https://docs.checkr.confluence/docs/networking_4",
    "CKV_AWS_2": "https://docs.checkr.confluence/docs/networking_29",
    "CKV_AWS_23": "https://docs.checkr.confluence/docs/networking_31",
    "CKV_AWS_34": "https://docs.checkr.confluence/docs/networking_32",
    "CKV_AWS_38": "https://docs.checkr.confluence/docs/bc_aws_kubernetes_1",
    "CKV_AWS_10": "https://docs.checkr.confluence/docs/iam_9-1",
    "CKV_AWS_39": "https://docs.checkr.confluence/docs/bc_aws_kubernetes_2",
    "CKV_AWS_58": "https://docs.checkr.confluence/docs/bc_aws_kubernetes_3",
    "CKV_AWS_37": "https://docs.checkr.confluence/docs/bc_aws_kubernetes_4",
    "CKV_AWS_50": "https://docs.checkr.confluence/docs/bc_aws_serverless_4",
    "CKV_AWS_3": "https://docs.checkr.confluence/docs/general_3-encrypt-eps-volume",
    "CKV_AWS_16": "https://docs.checkr.confluence/docs/general_4",
    "CKV_AWS_28": "https://docs.checkr.confluence/docs/general_6",
    "CKV_AWS_4": "https://docs.checkr.confluence/docs/general_7",
    "CKV_AWS_163": "https://docs.checkr.confluence/docs/general_8",
    "CKV_AWS_29": "https://docs.checkr.confluence/docs/general_9",
    "CKV_AWS_30": "https://docs.checkr.confluence/docs/general_10",
    "CKV_AWS_31": "https://docs.checkr.confluence/docs/general_11",
    "CKV_AWS_8": "https://docs.checkr.confluence/docs/general_13",
    "CKV_AWS_22": "https://docs.checkr.confluence/docs/general_14",
    "CKV_AWS_26": "https://docs.checkr.confluence/docs/general_15",
    "CKV_AWS_27": "https://docs.checkr.confluence/docs/general_16-encrypt-sqs-queue",
    "CKV_AWS_42": "https://docs.checkr.confluence/docs/general_17",
    "CKV_AWS_44": "https://docs.checkr.confluence/docs/general_18",
    "CKV_AWS_43": "https://docs.checkr.confluence/docs/bc_aws_general_22",
    "CKV_AWS_47": "https://docs.checkr.confluence/docs/bc_aws_general_23",
    "CKV_AWS_51": "https://docs.checkr.confluence/docs/bc_aws_general_24",
    "CKV_AWS_64": "https://docs.checkr.confluence/docs/general_25",
    "CKV_AWS_71": "https://docs.checkr.confluence/docs/bc_aws_logging_12",
    "CKV_AWS_CUSTOM_1": "https://docs.checkr.confluence/docs/bc_aws_general_26",
    "CKV_AWS_5": "https://docs.checkr.confluence/docs/elasticsearch_3-enable-encryptionatrest",
    "CKV_AWS_6": "https://docs.checkr.confluence/docs/elasticsearch_5",
    "CKV_AWS_83": "https://docs.checkr.confluence/docs/elasticsearch_6",
    "CKV_AWS_20": "https://docs.checkr.confluence/docs/s3_1-acl-read-permissions-everyone",
    "CKV_AWS_57": "https://docs.checkr.confluence/docs/s3_2-acl-write-permissions-everyone",
    "CKV_AWS_18": "https://docs.checkr.confluence/docs/s3_13-enable-logging",
    "CKV_AWS_19": "https://docs.checkr.confluence/docs/s3_14-data-encrypted-at-rest",
    "CKV_AWS_21": "https://docs.checkr.confluence/docs/s3_16-enable-versioning",
    "CKV_AWS_53": "https://docs.checkr.confluence/docs/bc_aws_s3_19",
    "CKV_AWS_54": "https://docs.checkr.confluence/docs/bc_aws_s3_20",
    "CKV_AWS_55": "https://docs.checkr.confluence/docs/bc_aws_s3_21",
    "CKV_AWS_56": "https://docs.checkr.confluence/docs/bc_aws_s3_22",
    "CKV_AWS_70": "https://docs.checkr.confluence/docs/bc_aws_s3_23",
    "CKV_AWS_46": "https://docs.checkr.confluence/docs/bc_aws_secrets_1",
    "CKV_AWS_45": "https://docs.checkr.confluence/docs/bc_aws_secrets_3",
    "CKV_AWS_41": "https://docs.checkr.confluence/docs/bc_aws_secrets_5",
    "CKV_AWS_32": "https://docs.checkr.confluence/docs/public_1-ecr-repositories-not-public",
    "CKV_AWS_17": "https://docs.checkr.confluence/docs/public_2",
    "CKV_AWS_59": "https://docs.checkr.confluence/docs/public_6-api-gateway-authorizer-set",
    "CKV_AWS_87": "https://docs.checkr.confluence/docs/public_9",
    "CKV_K8S_1": "https://docs.checkr.confluence/docs/bc_k8s_1",
    "CKV_K8S_2": "https://docs.checkr.confluence/docs/bc_k8s_2",
    "CKV_K8S_3": "https://docs.checkr.confluence/docs/bc_k8s_3",
    "CKV_K8S_4": "https://docs.checkr.confluence/docs/bc_k8s_4",
    "CKV_K8S_6": "https://docs.checkr.confluence/docs/bc_k8s_5",
    "CKV_K8S_7": "https://docs.checkr.confluence/docs/bc_k8s_6",
    "CKV_K8S_8": "https://docs.checkr.confluence/docs/bc_k8s_7",
    "CKV_K8S_9": "https://docs.checkr.confluence/docs/bc_k8s_8",
    "CKV_K8S_10": "https://docs.checkr.confluence/docs/bc_k8s_9",
    "CKV_K8S_11": "https://docs.checkr.confluence/docs/bc_k8s_10",
    "CKV_K8S_12": "https://docs.checkr.confluence/docs/bc_k8s_11",
    "CKV_K8S_13": "https://docs.checkr.confluence/docs/bc_k8s_12",
    "CKV_K8S_14": "https://docs.checkr.confluence/docs/bc_k8s_13",
    "CKV_K8S_15": "https://docs.checkr.confluence/docs/bc_k8s_14",
    "CKV_K8S_16": "https://docs.checkr.confluence/docs/bc_k8s_15",
    "CKV_K8S_17": "https://docs.checkr.confluence/docs/bc_k8s_16",
    "CKV_K8S_18": "https://docs.checkr.confluence/docs/bc_k8s_17",
    "CKV_K8S_19": "https://docs.checkr.confluence/docs/bc_k8s_18",
    "CKV_K8S_20": "https://docs.checkr.confluence/docs/bc_k8s_19",
    "CKV_K8S_21": "https://docs.checkr.confluence/docs/bc_k8s_20",
    "CKV_K8S_22": "https://docs.checkr.confluence/docs/bc_k8s_21",
    "CKV_K8S_23": "https://docs.checkr.confluence/docs/bc_k8s_22",
    "CKV_K8S_24": "https://docs.checkr.confluence/docs/bc_k8s_23",
    "CKV_K8S_25": "https://docs.checkr.confluence/docs/bc_k8s_24",
    "CKV_K8S_26": "https://docs.checkr.confluence/docs/bc_k8s_25",
    "CKV_K8S_27": "https://docs.checkr.confluence/docs/bc_k8s_26",
    "CKV_K8S_28": "https://docs.checkr.confluence/docs/bc_k8s_27",
    "CKV_K8S_30": "https://docs.checkr.confluence/docs/bc_k8s_28",
    "CKV_K8S_31": "https://docs.checkr.confluence/docs/bc_k8s_29",
    "CKV_K8S_32": "https://docs.checkr.confluence/docs/bc_k8s_30",
    "CKV_K8S_33": "https://docs.checkr.confluence/docs/bc_k8s_31",
    "CKV_K8S_34": "https://docs.checkr.confluence/docs/bc_k8s_32",
    "CKV_K8S_35": "https://docs.checkr.confluence/docs/bc_k8s_33",
    "CKV_K8S_37": "https://docs.checkr.confluence/docs/bc_k8s_34",
    "CKV_K8S_38": "https://docs.checkr.confluence/docs/bc_k8s_35",
    "CKV_K8S_40": "https://docs.checkr.confluence/docs/bc_k8s_37",
    "CKV_K8S_41": "https://docs.checkr.confluence/docs/bc_k8s_38",
    "CKV_K8S_43": "https://docs.checkr.confluence/docs/bc_k8s_39",
    "CKV_K8S_45": "https://docs.checkr.confluence/docs/bc_k8s_40",
    "CKV_K8S_44": "https://docs.checkr.confluence/docs/bc_k8s_41",
    "CKV_GCP_1": "https://docs.checkr.confluence/docs/bc_gcp_kubernetes_1",
    "CKV_GCP_7": "https://docs.checkr.confluence/docs/bc_gcp_kubernetes_2",
    "CKV_GCP_8": "https://docs.checkr.confluence/docs/bc_gcp_kubernetes_3",
    "CKV_GCP_9": "https://docs.checkr.confluence/docs/bc_gcp_kubernetes_4",
    "CKV_GCP_10": "https://docs.checkr.confluence/docs/bc_gcp_kubernetes_5",
    "CKV_GCP_25": "https://docs.checkr.confluence/docs/bc_gcp_kubernetes_6",
    "CKV_GCP_12": "https://docs.checkr.confluence/docs/bc_gcp_kubernetes_7",
    "CKV_GCP_13": "https://docs.checkr.confluence/docs/bc_gcp_kubernetes_8",
    "CKV_GCP_24": "https://docs.checkr.confluence/docs/bc_gcp_kubernetes_9",
    "CKV_GCP_18": "https://docs.checkr.confluence/docs/bc_gcp_kubernetes_10",
    "CKV_GCP_19": "https://docs.checkr.confluence/docs/bc_gcp_kubernetes_11",
    "CKV_GCP_20": "https://docs.checkr.confluence/docs/bc_gcp_kubernetes_12",
    "CKV_GCP_21": "https://docs.checkr.confluence/docs/bc_gcp_kubernetes_13",
    "CKV_GCP_22": "https://docs.checkr.confluence/docs/bc_gcp_kubernetes_14",
    "CKV_GCP_23": "https://docs.checkr.confluence/docs/bc_gcp_kubernetes_15",
    "CKV_GCP_2": "https://docs.checkr.confluence/docs/bc_gcp_networking_1",
    "CKV_GCP_3": "https://docs.checkr.confluence/docs/bc_gcp_networking_2",
    "CKV_GCP_4": "https://docs.checkr.confluence/docs/bc_gcp_networking_3",
    "CKV_GCP_11": "https://docs.checkr.confluence/docs/bc_gcp_networking_4",
    "CKV_GCP_16": "https://docs.checkr.confluence/docs/bc_gcp_networking_5",
    "CKV_GCP_17": "https://docs.checkr.confluence/docs/bc_gcp_networking_6",
    "CKV_GCP_27": "https://docs.checkr.confluence/docs/bc_gcp_networking_7",
    "CKV_GCP_32": "https://docs.checkr.confluence/docs/bc_gcp_networking_8",
    "CKV_GCP_33": "https://docs.checkr.confluence/docs/bc_gcp_networking_9",
    "CKV_GCP_34": "https://docs.checkr.confluence/docs/bc_gcp_networking_10",
    "CKV_GCP_35": "https://docs.checkr.confluence/docs/bc_gcp_networking_11",
    "CKV_GCP_36": "https://docs.checkr.confluence/docs/bc_gcp_networking_12",
    "CKV_GCP_37": "https://docs.checkr.confluence/docs/bc_gcp_general_x",
    "CKV_GCP_38": "https://docs.checkr.confluence/docs/encrypt-boot-disks-for-instances-with-cseks",
    "CKV_GCP_39": "https://docs.checkr.confluence/docs/bc_gcp_general_y",
    "CKV_GCP_43": "https://docs.checkr.confluence/docs/bc_gcp_general_4",
    "CKV_GCP_6": "https://docs.checkr.confluence/docs/bc_gcp_general_1",
    "CKV_GCP_14": "https://docs.checkr.confluence/docs/bc_gcp_general_2",
    "CKV_GCP_15": "https://docs.checkr.confluence/docs/bc_gcp_general_3",
    "CKV_GCP_28": "https://docs.checkr.confluence/docs/bc_gcp_public_1",
    "CKV_GCP_40": "https://docs.checkr.confluence/docs/bc_gcp_public_2",
    "CKV_GCP_30": "https://docs.checkr.confluence/docs/bc_gcp_iam_1",
    "CKV_GCP_31": "https://docs.checkr.confluence/docs/bc_gcp_iam_2",
    "CKV_GCP_41": "https://docs.checkr.confluence/docs/bc_gcp_iam_3",
    "CKV_GCP_42": "https://docs.checkr.confluence/docs/bc_gcp_iam_4",
    "CKV_GCP_26": "https://docs.checkr.confluence/docs/bc_gcp_logging_1",
    "CKV_GCP_5": "https://docs.checkr.confluence/docs/bc_gcp_gcs_1",
    "CKV_GCP_29": "https://docs.checkr.confluence/docs/bc_gcp_gcs_2",
    "CKV_AZURE_1": "https://docs.checkr.confluence/docs/bc_azr_networking_1",
    "CKV_AZURE_9": "https://docs.checkr.confluence/docs/bc_azr_networking_2",
    "CKV_AZURE_10": "https://docs.checkr.confluence/docs/bc_azr_networking_3",
    "CKV_AZURE_11": "https://docs.checkr.confluence/docs/bc_azr_networking_4",
    "CKV_AZURE_14": "https://docs.checkr.confluence/docs/bc_azr_networking_5",
    "CKV_AZURE_17": "https://docs.checkr.confluence/docs/bc_azr_networking_7",
    "CKV_AZURE_18": "https://docs.checkr.confluence/docs/bc_azr_networking_8",
    "CKV_AZURE_28": "https://docs.checkr.confluence/docs/bc_azr_networking_9",
    "CKV_AZURE_29": "https://docs.checkr.confluence/docs/bc_azr_networking_10",
    "CKV_AZURE_30": "https://docs.checkr.confluence/docs/bc_azr_networking_11",
    "CKV_AZURE_31": "https://docs.checkr.confluence/docs/bc_azr_networking_12",
    "CKV_AZURE_32": "https://docs.checkr.confluence/docs/bc_azr_networking_13",
    "CKV_AZURE_34": "https://docs.checkr.confluence/docs/set-public-access-level-to-private-for-blob-containers",
    "CKV_AZURE_35": "https://docs.checkr.confluence/docs/set-default-network-access-rule-for-storage-accounts-to-deny",
    "CKV_AZURE_36": "https://docs.checkr.confluence/docs/enable-trusted-microsoft-services-for-storage-account-access",
    "CKV_AZURE_12": "https://docs.checkr.confluence/docs/bc_azr_logging_1",
    "CKV_AZURE_23": "https://docs.checkr.confluence/docs/bc_azr_logging_2",
    "CKV_AZURE_24": "https://docs.checkr.confluence/docs/bc_azr_logging_3",
    "CKV_AZURE_33": "https://docs.checkr.confluence/docs/enable-requests-on-storage-logging-for-queue-service",
    "CKV_AZURE_37": "https://docs.checkr.confluence/docs/set-activity-log-retention-to-365-days-or-greater",
    "CKV_AZURE_38": "https://docs.checkr.confluence/docs/ensure-audit-profile-captures-all-activities",
    "CKV_AZURE_2": "https://docs.checkr.confluence/docs/bc_azr_general_1",
    "CKV_AZURE_13": "https://docs.checkr.confluence/docs/bc_azr_general_2",
    "CKV_AZURE_20": "https://docs.checkr.confluence/docs/bc_azr_general_3",
    "CKV_AZURE_21": "https://docs.checkr.confluence/docs/bc_azr_general_4",
    "CKV_AZURE_22": "https://docs.checkr.confluence/docs/bc_azr_general_5",
    "CKV_AZURE_25": "https://docs.checkr.confluence/docs/bc_azr_general_6",
    "CKV_AZURE_26": "https://docs.checkr.confluence/docs/bc_azr_general_7",
    "CKV_AZURE_27": "https://docs.checkr.confluence/docs/bc_azr_general_8",
    "CKV_AZURE_19": "https://docs.checkr.confluence/docs/ensure-standard-pricing-tier-is-selected",
    "CKV_AZURE_40": "https://docs.checkr.confluence/docs/set-an-expiration-date-on-all-keys",
    "CKV_AZURE_42": "https://docs.checkr.confluence/docs/ensure-the-key-vault-is-recoverable",
    "CKV_AZURE_16": "https://docs.checkr.confluence/docs/bc_azr_iam_1",
    "CKV_AZURE_39": "https://docs.checkr.confluence/docs/do-not-create-custom-subscription-owner-roles",
    "CKV_AZURE_3": "https://docs.checkr.confluence/docs/ensure-secure-transfer-required-is-enabled",
    "CKV_AZURE_41": "https://docs.checkr.confluence/docs/set-an-expiration-date-on-all-secrets",
    "CKV_AZURE_45": "https://docs.checkr.confluence/docs/set-an-expiration-date-on-all-secrets",
    "CKV_AZURE_4": "https://docs.checkr.confluence/docs/bc_azr_kubernetes_1",
    "CKV_AZURE_5": "https://docs.checkr.confluence/docs/bc_azr_kubernetes_2",
    "CKV_AZURE_6": "https://docs.checkr.confluence/docs/bc_azr_kubernetes_3",
    "CKV_AZURE_7": "https://docs.checkr.confluence/docs/bc_azr_kubernetes_4",
    "CKV_AZURE_8": "https://docs.checkr.confluence/docs/bc_azr_kubernetes_5",
    "CKV_AWS_62": "https://docs.checkr.confluence/docs/iam_47",
    "CKV_AWS_63": "https://docs.checkr.confluence/docs/iam_48",
    "CKV_AWS_66": "https://docs.checkr.confluence/docs/logging_13",
    "CKV_AWS_68": "https://docs.checkr.confluence/docs/bc_aws_general_27",
    "CKV_AWS_69": "https://docs.checkr.confluence/docs/public_11",
    "CKV_AWS_73": "https://docs.checkr.confluence/docs/logging_15",
    "CKV_AWS_74": "https://docs.checkr.confluence/docs/bc_aws_general_28",
    "CKV_AWS_132": "https://docs.checkr.confluence/docs/ensure-kms-have-rotation-policy",
    "CKV_AWS_75": "https://docs.checkr.confluence/docs/logging_16",
    "CKV_AWS_76": "https://docs.checkr.confluence/docs/logging_17",
    "CKV_AWS_78": "https://docs.checkr.confluence/docs/bc_aws_general_30",
    "CKV_AWS_79": "https://docs.checkr.confluence/docs/bc_aws_general_31",
    "CKV_AWS_80": "https://docs.checkr.confluence/docs/logging_18",
    "CKV_AWS_81": "https://docs.checkr.confluence/docs/bc_aws_general_32",
    "CKV_AWS_82": "https://docs.checkr.confluence/docs/bc_aws_general_33",
    "CKV_AWS_84": "https://docs.checkr.confluence/docs/elasticsearch_7",
    "CKV_AWS_85": "https://docs.checkr.confluence/docs/logging_19",
    "CKV_AWS_86": "https://docs.checkr.confluence/docs/logging_20",
    "CKV_AWS_CUSTOM_2": "https://docs.checkr.confluence/docs/logging_21",
    "CKV_AZURE_44": "https://docs.checkr.confluence/docs/bc_azr_storage_2",
    "CKV_GCP_44": "https://docs.checkr.confluence/docs/bc_gcp_iam_5",
    "CKV_GCP_45": "https://docs.checkr.confluence/docs/bc_gcp_iam_6",
    "CKV_GCP_46": "https://docs.checkr.confluence/docs/bc_gcp_iam_7",
    "CKV_GCP_47": "https://docs.checkr.confluence/docs/bc_gcp_iam_8",
    "CKV_GCP_48": "https://docs.checkr.confluence/docs/bc_gcp_iam_9",
    "CKV_GCP_49": "https://docs.checkr.confluence/docs/bc_gcp_iam_10",
    "CKV_GCP_50": "https://docs.checkr.confluence/docs/bc_gcp_sql_1",
    "CKV_GCP_51": "https://docs.checkr.confluence/docs/bc_gcp_sql_2",
    "CKV_GCP_52": "https://docs.checkr.confluence/docs/bc_gcp_sql_3",
    "CKV_GCP_53": "https://docs.checkr.confluence/docs/bc_gcp_sql_4",
    "CKV_GCP_54": "https://docs.checkr.confluence/docs/bc_gcp_sql_5",
    "CKV_GCP_55": "https://docs.checkr.confluence/docs/bc_gcp_sql_6",
    "CKV_GCP_56": "https://docs.checkr.confluence/docs/bc_gcp_sql_7",
    "CKV_GCP_57": "https://docs.checkr.confluence/docs/bc_gcp_sql_8",
    "CKV_GCP_58": "https://docs.checkr.confluence/docs/bc_gcp_sql_9",
    "CKV_GCP_59": "https://docs.checkr.confluence/docs/bc_gcp_sql_10",
    "CKV_GCP_60": "https://docs.checkr.confluence/docs/bc_gcp_sql_11",
    "CKV_K8S_5": "https://docs.checkr.confluence/docs/bc_k8s_19",
    "CKV_K8S_29": "https://docs.checkr.confluence/docs/bc_k8s_28",
    "CKV_K8S_36": "https://docs.checkr.confluence/docs/bc_k8s_34",
    "CKV_K8S_42": "https://docs.checkr.confluence/docs/bc_k8s_38",
    "CKV_AWS_88": "https://docs.checkr.confluence/docs/public_12",
    "CKV_AWS_89": "https://docs.checkr.confluence/docs/public_13",
    "CKV_AWS_90": "https://docs.checkr.confluence/docs/bc_aws_networking_37",
    "CKV_AWS_91": "https://docs.checkr.confluence/docs/bc_aws_logging_22",
    "CKV_AWS_92": "https://docs.checkr.confluence/docs/bc_aws_logging_23",
    "CKV_AWS_93": "https://docs.checkr.confluence/docs/bc_aws_iam_53",
    "CKV_AWS_94": "https://docs.checkr.confluence/docs/bc_aws_general_37",
    "CKV_AWS_96": "https://docs.checkr.confluence/docs/bc_aws_general_38",
    "CKV_AWS_97": "https://docs.checkr.confluence/docs/bc_aws_general_39",
    "CKV_AWS_98": "https://docs.checkr.confluence/docs/bc_aws_general_40",
    "CKV_AWS_99": "https://docs.checkr.confluence/docs/bc_aws_general_41",
    "CKV_AWS_100": "https://docs.checkr.confluence/docs/bc_aws_kubernetes_5",
    "CKV_AWS_101": "https://docs.checkr.confluence/docs/bc_aws_logging_24",
    "CKV_AWS_102": "https://docs.checkr.confluence/docs/bc_aws_general_42",
    "CKV_AWS_103": "https://docs.checkr.confluence/docs/bc_aws_general_43",
    "CKV_AZURE_46": "https://docs.checkr.confluence/docs/bc_azr_general_12",
    "CKV_AZURE_47": "https://docs.checkr.confluence/docs/bc_azr_networking_17",
    "CKV_AZURE_48": "https://docs.checkr.confluence/docs/bc_azr_public_1",
    "CKV_AZURE_49": "https://docs.checkr.confluence/docs/bc_azr_general_13",
    "CKV_GCP_62": "https://docs.checkr.confluence/docs/bc_gcp_logging_2",
    "CKV_AZURE_50": "https://docs.checkr.confluence/docs/bc_azr_general_14",
    "CKV_GCP_63": "https://docs.checkr.confluence/docs/bc_gcp_logging_3",
    "CKV_AWS_106": "https://docs.checkr.confluence/docs/ensure-kubernetes-secrets-are-encrypted-using-customer-master-keys-cmks-managed-in-aws-kms",
    "CKV_AWS_107": "https://docs.checkr.confluence/docs/ensure-iam-policies-do-not-allow-credentials-exposure",
    "CKV_AWS_108": "https://docs.checkr.confluence/docs/ensure-iam-policies-do-not-allow-data-exfiltration",
    "CKV_AWS_109": "https://docs.checkr.confluence/docs/ensure-iam-policies-do-not-allow-permissions-management-resource-exposure-without-constraint",
    "CKV_AWS_111": "https://docs.checkr.confluence/docs/ensure-iam-policies-do-not-allow-write-access-without-constraint",
    "CKV_AWS_113": "https://docs.checkr.confluence/docs/ensure-that-load-balancer-has-deletion-protection-enabled",
    "CKV_AWS_114": "https://docs.checkr.confluence/docs/ensure-that-emr-clusters-have-kerberos-enabled",
    "CKV_AWS_115": "https://docs.checkr.confluence/docs/ensure-that-aws-lambda-function-is-configured-for-function-level-concurrent-execution-limit",
    "CKV_AWS_116": "https://docs.checkr.confluence/docs/ensure-that-aws-lambda-function-is-configured-for-a-dead-letter-queue-dlq",
    "CKV_AWS_117": "https://docs.checkr.confluence/docs/ensure-that-aws-lambda-function-is-configured-inside-a-vpc-1",
    "CKV_AWS_118": "https://docs.checkr.confluence/docs/ensure-that-enhanced-monitoring-is-enabled-for-amazon-rds-instances",
    "CKV_AWS_119": "https://docs.checkr.confluence/docs/ensure-that-dynamodb-tables-are-encrypted",
    "CKV2_AWS_16": "https://docs.checkr.confluence/docs/ensure-that-auto-scaling-is-enabled-on-your-dynamodb-tables",
    "CKV_AWS_122": "https://docs.checkr.confluence/docs/ensure-that-direct-internet-access-is-disabled-for-an-amazon-sagemaker-notebook-instance",
    "CKV_AWS_123": "https://docs.checkr.confluence/docs/ensure-that-vpc-endpoint-service-is-configured-for-manual-acceptance",
    "CKV_AWS_124": "https://docs.checkr.confluence/docs/ensure-that-cloudformation-stacks-are-sending-event-notifications-to-an-sns-topic",
    "CKV_AWS_126": "https://docs.checkr.confluence/docs/ensure-that-detailed-monitoring-is-enabled-for-ec2-instances",
    "CKV_AWS_127": "https://docs.checkr.confluence/docs/ensure-that-elastic-load-balancers-uses-ssl-certificates-provided-by-aws-certificate-manager",
    "CKV_AWS_128": "https://docs.checkr.confluence/docs/ensure-that-an-amazon-rds-clusters-have-iam-authentication-enabled",
    "CKV_AWS_129": "https://docs.checkr.confluence/docs/ensure-that-respective-logs-of-amazon-relational-database-service-amazon-rds-are-enabled",
    "CKV_AWS_131": "https://docs.checkr.confluence/docs/ensure-that-alb-drops-http-headers",
    "CKV_AWS_133": "https://docs.checkr.confluence/docs/ensure-that-rds-instances-have-backup-policy",
    "CKV_AWS_134": "https://docs.checkr.confluence/docs/ensure-that-amazon-elasticache-redis-clusters-have-automatic-backup-turned-on",
    "CKV_AWS_135": "https://docs.checkr.confluence/docs/ensure-that-ec2-is-ebs-optimized",
    "CKV_AWS_136": "https://docs.checkr.confluence/docs/ensure-that-ecr-repositories-are-encrypted",
    "CKV_AWS_137": "https://docs.checkr.confluence/docs/ensure-that-elasticsearch-is-configured-inside-a-vpc",
    "CKV_AWS_138": "https://docs.checkr.confluence/docs/ensure-that-elb-is-cross-zone-load-balancing-enabled",
    "CKV_AWS_139": "https://docs.checkr.confluence/docs/ensure-that-rds-clusters-and-instances-have-deletion-protection-enabled",
    "CKV_AWS_140": "https://docs.checkr.confluence/docs/ensure-that-rds-global-clusters-are-encrypted",
    "CKV_AWS_141": "https://docs.checkr.confluence/docs/ensure-that-redshift-clusters-allow-version-upgrade-by-default",
    "CKV_AWS_142": "https://docs.checkr.confluence/docs/ensure-that-redshift-cluster-is-encrypted-by-kms",
    "CKV_AWS_143": "https://docs.checkr.confluence/docs/ensure-that-s3-bucket-has-lock-configuration-enabled-by-default",
    "CKV_AWS_144": "https://docs.checkr.confluence/docs/ensure-that-s3-bucket-has-cross-region-replication-enabled",
    "CKV_AWS_157": "https://docs.checkr.confluence/docs/general_73",
    "CKV_AWS_13": "https://docs.checkr.confluence/docs/iam_10",
    "CKV_AWS_145": "https://docs.checkr.confluence/docs/ensure-that-s3-buckets-are-encrypted-with-kms-by-default",
    "CKV2_AWS_1": "https://docs.checkr.confluence/docs/ensure-that-all-nacl-are-attached-to-subnets",
    "CKV2_AWS_2": "https://docs.checkr.confluence/docs/ensure-that-only-encrypted-ebs-volumes-are-attached-to-ec2-instances",
    "CKV2_AWS_3": "https://docs.checkr.confluence/docs/ensure-guardduty-is-enabled-to-specific-orgregion",
    "CKV2_AWS_4": "https://docs.checkr.confluence/docs/ensure-api-gateway-stage-have-logging-level-defined-as-appropiate",
    "CKV2_AWS_5": "https://docs.checkr.confluence/docs/ensure-that-security-groups-are-attached-to-ec2-instances-or-elastic-network-interfaces-enis",
    "CKV2_AWS_6": "https://docs.checkr.confluence/docs/s3-bucket-should-have-public-access-blocks-defaults-to-false-if-the-public-access-block-is-not-attached",
    "CKV2_AWS_7": "https://docs.checkr.confluence/docs/ensure-that-amazon-emr-clusters-security-groups-are-not-open-to-the-world",
    "CKV2_AWS_8": "https://docs.checkr.confluence/docs/ensure-that-rds-clusters-has-backup-plan-of-aws-backup",
    "CKV2_AWS_9": "https://docs.checkr.confluence/docs/ensure-that-ebs-are-added-in-the-backup-plans-of-aws-backup",
    "CKV2_AWS_10": "https://docs.checkr.confluence/docs/ensure-cloudtrail-trails-are-integrated-with-cloudwatch-logs",
    "CKV2_AWS_13": "https://docs.checkr.confluence/docs/ensure-that-redshift-clusters-has-backup-plan-of-aws-backup",
    "CKV2_AWS_14": "https://docs.checkr.confluence/docs/ensure-that-iam-groups-include-at-least-one-iam-user",
    "CKV2_AWS_15": "https://docs.checkr.confluence/docs/ensure-that-auto-scaling-groups-that-are-associated-with-a-load-balancer-are-using-elastic-load-balancing-health-checks",
    "CKV2_AWS_17": "https://docs.checkr.confluence/docs/ensure-that-ec2-instances-belong-to-a-vpc",
    "CKV2_AWS_18": "https://docs.checkr.confluence/docs/ensure-that-elastic-file-system-amazon-efs-file-systems-are-added-in-the-backup-plans-of-aws-backup",
    "CKV2_AWS_19": "https://docs.checkr.confluence/docs/ensure-that-all-eip-addresses-allocated-to-a-vpc-are-attached-to-ec2-instances",
    "CKV2_AWS_20": "https://docs.checkr.confluence/docs/ensure-that-alb-redirects-http-requests-into-https-ones",
    "CKV2_AWS_21": "https://docs.checkr.confluence/docs/ensure-that-all-iam-users-are-members-of-at-least-one-iam-group",
    "CKV_AZURE_55": "https://docs.checkr.confluence/docs/ensure-that-azure-defender-is-set-to-on-for-servers",
    "CKV_AZURE_56": "https://docs.checkr.confluence/docs/ensure-that-function-apps-enables-authentication",
    "CKV_AZURE_57": "https://docs.checkr.confluence/docs/ensure-that-cors-disallows-every-resource-to-access-app-services",
    "CKV_AZURE_58": "https://docs.checkr.confluence/docs/ensure-that-azure-synapse-workspaces-enables-managed-virtual-networks",
    "CKV_AZURE_59": "https://docs.checkr.confluence/docs/ensure-that-storage-accounts-disallow-public-access",
    "CKV_AZURE_60": "https://docs.checkr.confluence/docs/ensure-that-storage-account-enables-secure-transfer",
    "CKV_AZURE_61": "https://docs.checkr.confluence/docs/ensure-that-azure-defender-is-set-to-on-for-app-service",
    "CKV_AZURE_62": "https://docs.checkr.confluence/docs/ensure-that-cors-disallows-every-resource-to-access-function-apps",
    "CKV_AZURE_63": "https://docs.checkr.confluence/docs/ensure-that-app-service-enables-http-logging",
    "CKV_AZURE_64": "https://docs.checkr.confluence/docs/ensure-that-azure-file-sync-disables-public-network-access",
    "CKV_AZURE_65": "https://docs.checkr.confluence/docs/tbdensure-that-app-service-enables-detailed-error-messages",
    "CKV_AZURE_66": "https://docs.checkr.confluence/docs/ensure-that-app-service-enables-failed-request-tracing",
    "CKV_AZURE_67": "https://docs.checkr.confluence/docs/ensure-that-http-version-is-the-latest-if-used-to-run-the-function-app",
    "CKV_AZURE_68": "https://docs.checkr.confluence/docs/ensure-that-postgresql-server-disables-public-network-access",
    "CKV_AZURE_69": "https://docs.checkr.confluence/docs/ensure-that-azure-defender-is-set-to-on-for-azure-sql-database-servers",
    "CKV_AZURE_70": "https://docs.checkr.confluence/docs/ensure-that-function-apps-is-only-accessible-over-https",
    "CKV_AZURE_71": "https://docs.checkr.confluence/docs/ensure-that-managed-identity-provider-is-enabled-for-app-services",
    "CKV_AZURE_72": "https://docs.checkr.confluence/docs/ensure-that-remote-debugging-is-not-enabled-for-app-services",
    "CKV_AZURE_73": "https://docs.checkr.confluence/docs/ensure-that-automation-account-variables-are-encrypted",
    "CKV_AZURE_74": "https://docs.checkr.confluence/docs/ensure-that-azure-data-explorer-uses-disk-encryption",
    "CKV_AZURE_75": "https://docs.checkr.confluence/docs/ensure-that-azure-data-explorer-uses-double-encryption",
    "CKV_AZURE_76": "https://docs.checkr.confluence/docs/ensure-that-azure-batch-account-uses-key-vault-to-encrypt-data",
    "CKV_AZURE_77": "https://docs.checkr.confluence/docs/ensure-that-udp-services-are-restricted-from-the-internet",
    "CKV_AZURE_78": "https://docs.checkr.confluence/docs/ensure-ftp-deployments-are-disabled",
    "CKV_AZURE_79": "https://docs.checkr.confluence/docs/ensure-that-azure-defender-is-set-to-on-for-sql-servers-on-machines",
    "CKV_AZURE_80": "https://docs.checkr.confluence/docs/ensure-that-net-framework-version-is-the-latest-if-used-as-a-part-of-the-web-app",
    "CKV_AZURE_81": "https://docs.checkr.confluence/docs/ensure-that-php-version-is-the-latest-if-used-to-run-the-web-app",
    "CKV_AZURE_82": "https://docs.checkr.confluence/docs/ensure-that-python-version-is-the-latest-if-used-to-run-the-web-app",
    "CKV_AZURE_83": "https://docs.checkr.confluence/docs/ensure-that-java-version-is-the-latest-if-used-to-run-the-web-app",
    "CKV_AZURE_84": "https://docs.checkr.confluence/docs/ensure-that-azure-defender-is-set-to-on-for-storage",
    "CKV_AZURE_85": "https://docs.checkr.confluence/docs/ensure-that-azure-defender-is-set-to-on-for-kubernetes",
    "CKV_AZURE_86": "https://docs.checkr.confluence/docs/ensure-that-azure-defender-is-set-to-on-for-container-registries",
    "CKV_AZURE_87": "https://docs.checkr.confluence/docs/ensure-that-azure-defender-is-set-to-on-for-key-vault",
    "CKV_AZURE_88": "https://docs.checkr.confluence/docs/ensure-that-app-services-use-azure-files",
    "CKV_AZURE_89": "https://docs.checkr.confluence/docs/ensure-that-azure-cache-for-redis-disables-public-network-access",
    "CKV_AZURE_90": "https://docs.checkr.confluence/docs/ensure-that-mysql-server-disables-public-network-access",
    "CKV_AZURE_91": "https://docs.checkr.confluence/docs/ensure-that-only-ssl-are-enabled-for-cache-for-redis",
    "CKV_AZURE_92": "https://docs.checkr.confluence/docs/ensure-that-virtual-machines-use-managed-disks",
    "CKV_AZURE_93": "https://docs.checkr.confluence/docs/ensure-that-managed-disks-use-a-specific-set-of-disk-encryption-sets-for-the-customer-managed-key-encryption",
    "CKV_AZURE_94": "https://docs.checkr.confluence/docs/ensure-that-my-sql-server-enables-geo-redundant-backups",
    "CKV_AZURE_95": "https://docs.checkr.confluence/docs/ensure-that-automatic-os-image-patching-is-enabled-for-virtual-machine-scale-sets",
    "CKV_AZURE_96": "https://docs.checkr.confluence/docs/ensure-that-postgresql-server-enables-infrastructure-encryption-1",
    "CKV_AZURE_97": "https://docs.checkr.confluence/docs/ensure-that-virtual-machine-scale-sets-have-encryption-at-host-enabled",
    "CKV_AZURE_98": "https://docs.checkr.confluence/docs/ensure-that-azure-container-container-group-is-deployed-into-virtual-network",
    "CKV_AZURE_99": "https://docs.checkr.confluence/docs/ensure-cosmos-db-accounts-have-restricted-access",
    "CKV_AZURE_100": "https://docs.checkr.confluence/docs/ensure-that-cosmos-db-accounts-have-customer-managed-keys-to-encrypt-data-at-rest",
    "CKV_AZURE_101": "https://docs.checkr.confluence/docs/ensure-that-azure-cosmos-db-disables-public-network-access",
    "CKV_AZURE_102": "https://docs.checkr.confluence/docs/ensure-that-postgresql-server-enables-geo-redundant-backups",
    "CKV_AZURE_103": "https://docs.checkr.confluence/docs/ensure-that-azure-data-factory-uses-git-repository-for-source-control",
    "CKV_AZURE_104": "https://docs.checkr.confluence/docs/ensure-that-azure-data-factory-public-network-access-is-disabled",
    "CKV_AWS_9": "https://docs.checkr.confluence/docs/iam_11",
    "CKV_AZURE_105": "https://docs.checkr.confluence/docs/ensure-that-data-lake-store-accounts-enables-encryption",
    "CKV_AZURE_106": "https://docs.checkr.confluence/docs/ensure-that-azure-event-grid-domain-public-network-access-is-disabled",
    "CKV_AZURE_107": "https://docs.checkr.confluence/docs/ensure-that-api-management-services-uses-virtual-networks",
    "CKV_AZURE_108": "https://docs.checkr.confluence/docs/ensure-that-azure-iot-hub-disables-public-network-access",
    "CKV_AZURE_109": "https://docs.checkr.confluence/docs/ensure-that-key-vault-allows-firewall-rules-settings",
    "CKV_AZURE_110": "https://docs.checkr.confluence/docs/ensure-that-key-vault-enables-purge-protection",
    "CKV_AZURE_111": "https://docs.checkr.confluence/docs/ensure-that-key-vault-enables-soft-delete",
    "CKV_AZURE_112": "https://docs.checkr.confluence/docs/ensure-that-key-vault-key-is-backed-by-hsm",
    "CKV_AZURE_113": "https://docs.checkr.confluence/docs/ensure-that-sql-server-disables-public-network-access",
    "CKV_AZURE_114": "https://docs.checkr.confluence/docs/ensure-that-key-vault-secrets-have-content_type-set",
    "CKV_AZURE_115": "https://docs.checkr.confluence/docs/ensure-that-aks-enables-private-clusters",
    "CKV_AZURE_116": "https://docs.checkr.confluence/docs/ensure-that-aks-uses-azure-policies-add-on",
    "CKV_AZURE_117": "https://docs.checkr.confluence/docs/ensure-that-aks-uses-disk-encryption-set",
    "CKV_AZURE_118": "https://docs.checkr.confluence/docs/ensure-that-network-interfaces-disable-ip-forwarding",
    "CKV_AZURE_119": "https://docs.checkr.confluence/docs/ensure-that-network-interfaces-dont-use-public-ips",
    "CKV_AZURE_120": "https://docs.checkr.confluence/docs/ensure-that-application-gateway-enables-waf",
    "CKV_AZURE_121": "https://docs.checkr.confluence/docs/ensure-that-azure-front-door-enables-waf",
    "CKV_AZURE_122": "https://docs.checkr.confluence/docs/ensure-that-application-gateway-uses-waf-in-detection-or-prevention-modes",
    "CKV_AZURE_123": "https://docs.checkr.confluence/docs/ensure-that-azure-front-door-uses-waf-in-detection-or-prevention-modes",
    "CKV_AZURE_124": "https://docs.checkr.confluence/docs/ensure-that-azure-cognitive-search-disables-public-network-access",
    "CKV_AZURE_127": "https://docs.checkr.confluence/docs/ensure-that-my-sql-server-enables-threat-detection-policy",
    "CKV_AZURE_128": "https://docs.checkr.confluence/docs/ensure-that-postgresql-server-enables-threat-detection-policy",
    "CKV_AZURE_129": "https://docs.checkr.confluence/docs/ensure-that-mariadb-server-enables-geo-redundant-backups",
    "CKV_AZURE_130": "https://docs.checkr.confluence/docs/ensure-that-postgresql-server-enables-infrastructure-encryption",
    "CKV_AZURE_131": "https://docs.checkr.confluence/docs/ensure-that-security-contact-emails-is-set",
    "CKV2_AZURE_1": "https://docs.checkr.confluence/docs/ensure-storage-for-critical-data-are-encrypted-with-customer-managed-key",
    "CKV2_AZURE_2": "https://docs.checkr.confluence/docs/ensure-that-vulnerability-assessment-va-is-enabled-on-a-sql-server-by-setting-a-storage-account",
    "CKV2_AZURE_3": "https://docs.checkr.confluence/docs/ensure-that-va-setting-periodic-recurring-scans-is-enabled-on-a-sql-server",
    "CKV2_AZURE_4": "https://docs.checkr.confluence/docs/ensure-that-va-setting-send-scan-reports-to-is-configured-for-a-sql-server",
    "CKV2_AZURE_5": "https://docs.checkr.confluence/docs/ensure-that-va-setting-also-send-email-notifications-to-admins-and-subscription-owners-is-set-for-an-sql-server",
    "CKV2_AZURE_7": "https://docs.checkr.confluence/docs/ensure-that-azure-active-directory-admin-is-configured",
    "CKV2_AZURE_8": "https://docs.checkr.confluence/docs/ensure-the-storage-container-storing-the-activity-logs-is-not-publicly-accessible",
    "CKV2_AZURE_9": "https://docs.checkr.confluence/docs/ensure-virtual-machines-are-utilizing-managed-disks",
    "CKV2_AZURE_10": "https://docs.checkr.confluence/docs/ensure-that-microsoft-antimalware-is-configured-to-automatically-updates-for-virtual-machines",
    "CKV2_AZURE_11": "https://docs.checkr.confluence/docs/ensure-that-azure-data-explorer-encryption-at-rest-uses-a-customer-managed-key",
    "CKV2_AZURE_12": "https://docs.checkr.confluence/docs/ensure-that-virtual-machines-are-backed-up-using-azure-backup",
    "CKV2_AZURE_13": "https://docs.checkr.confluence/docs/ensure-that-sql-servers-enables-data-security-policy",
    "CKV2_AZURE_14": "https://docs.checkr.confluence/docs/ensure-that-unattached-disks-are-encrypted",
    "CKV2_AZURE_15": "https://docs.checkr.confluence/docs/ensure-that-azure-data-factories-are-encrypted-with-a-customer-managed-key",
    "CKV2_AZURE_16": "https://docs.checkr.confluence/docs/ensure-that-mysql-server-enables-customer-managed-key-for-encryption",
    "CKV2_AZURE_17": "https://docs.checkr.confluence/docs/ensure-that-postgresql-server-enables-customer-managed-key-for-encryption",
    "CKV2_AZURE_18": "https://docs.checkr.confluence/docs/ensure-that-storage-accounts-use-customer-managed-key-for-encryption",
    "CKV2_AZURE_19": "https://docs.checkr.confluence/docs/ensure-that-azure-synapse-workspaces-have-no-ip-firewall-rules-attached",
    "CKV2_AZURE_20": "https://docs.checkr.confluence/docs/ensure-storage-logging-is-enabled-for-table-service-for-read-requests",
    "CKV2_AZURE_21": "https://docs.checkr.confluence/docs/ensure-storage-logging-is-enabled-for-blob-service-for-read-requests",
    "CKV_GCP_61": "https://docs.checkr.confluence/docs/enable-vpc-flow-logs-and-intranode-visibility",
    "CKV_GCP_64": "https://docs.checkr.confluence/docs/ensure-clusters-are-created-with-private-nodes",
    "CKV_GCP_65": "https://docs.checkr.confluence/docs/manage-kubernetes-rbac-users-with-google-groups-for-gke",
    "CKV_GCP_66": "https://docs.checkr.confluence/docs/ensure-use-of-binary-authorization",
    "CKV_GCP_67": "https://docs.checkr.confluence/docs/ensure-legacy-compute-engine-instance-metadata-apis-are-disabled",
    "CKV_GCP_68": "https://docs.checkr.confluence/docs/ensure-secure-boot-for-shielded-gke-nodes-is-enabled",
    "CKV_GCP_69": "https://docs.checkr.confluence/docs/ensure-the-gke-metadata-server-is-enabled",
    "CKV_GCP_71": "https://docs.checkr.confluence/docs/ensure-shielded-gke-nodes-are-enabled",
    "CKV_GCP_72": "https://docs.checkr.confluence/docs/ensure-integrity-monitoring-for-shielded-gke-nodes-is-enabled",
    "CKV2_GCP_1": "https://docs.checkr.confluence/docs/ensure-gke-clusters-are-not-running-using-the-compute-engine-default-service-account",
    "CKV2_GCP_2": "https://docs.checkr.confluence/docs/ensure-legacy-networks-do-not-exist-for-a-project",
    "CKV2_GCP_3": "https://docs.checkr.confluence/docs/ensure-that-there-are-only-gcp-managed-service-account-keys-for-each-service-account",
    "CKV2_GCP_4": "https://docs.checkr.confluence/docs/ensure-that-retention-policies-on-log-buckets-are-configured-using-bucket-lock",
    "CKV2_GCP_5": "https://docs.checkr.confluence/docs/ensure-that-cloud-audit-logging-is-configured-properly-across-all-services-and-all-users-from-a-project",
    "CKV2_GCP_6": "https://docs.checkr.confluence/docs/ensure-that-cloud-kms-cryptokeys-are-not-anonymously-or-publicly-accessible",
    "CKV2_GCP_7": "https://docs.checkr.confluence/docs/ensure-that-a-mysql-database-instance-does-not-allow-anyone-to-connect-with-administrative-privileges",
    "CKV_K8S_68": "https://docs.checkr.confluence/docs/ensure-that-the-anonymous-auth-argument-is-set-to-false-1",
    "CKV_K8S_69": "https://docs.checkr.confluence/docs/ensure-that-the-basic-auth-file-argument-is-not-set",
    "CKV_K8S_70": "https://docs.checkr.confluence/docs/ensure-that-the-token-auth-file-parameter-is-not-set",
    "CKV_K8S_71": "https://docs.checkr.confluence/docs/ensure-that-the-kubelet-https-argument-is-set-to-true",
    "CKV_K8S_72": "https://docs.checkr.confluence/docs/ensure-that-the-kubelet-client-certificate-and-kubelet-client-key-arguments-are-set-as-appropriate",
    "CKV_K8S_73": "https://docs.checkr.confluence/docs/ensure-that-the-kubelet-certificate-authority-argument-is-set-as-appropriate",
    "CKV_K8S_74": "https://docs.checkr.confluence/docs/ensure-that-the-authorization-mode-argument-is-not-set-to-alwaysallow-1",
    "CKV_K8S_79": "https://docs.checkr.confluence/docs/ensure-that-the-admission-control-plugin-alwaysadmit-is-not-set",
    "CKV_AWS_15": "https://docs.checkr.confluence/docs/iam_5",
    "CKV_AWS_1": "https://docs.checkr.confluence/docs/iam_23",
    "CKV_AWS_121": "https://docs.checkr.confluence/docs/logging_5-enable-aws-config-regions",
    "CKV_AWS_35": "https://docs.checkr.confluence/docs/logging_7",
    "CKV_AWS_7": "https://docs.checkr.confluence/docs/logging_8",
    "CKV2_AWS_11": "https://docs.checkr.confluence/docs/logging_9-enable-vpc-flow-logging",
    "CKV_AWS_48": "https://docs.checkr.confluence/docs/bc_aws_logging_10",
    "CKV_K8S_39": "https://docs.checkr.confluence/docs/bc_k8s_36",
    "CKV_AZURE_15": "https://docs.checkr.confluence/docs/bc_azr_networking_6",
    "CKV_AWS_77": "https://docs.checkr.confluence/docs/bc_aws_general_29",
    "CKV_K8S_75": "https://docs.checkr.confluence/docs/ensure-that-the-authorization-mode-argument-includes-node",
    "CKV_K8S_77": "https://docs.checkr.confluence/docs/ensure-that-the-authorization-mode-argument-includes-rbac",
    "CKV_K8S_78": "https://docs.checkr.confluence/docs/ensure-that-the-admission-control-plugin-eventratelimit-is-set",
    "CKV_K8S_80": "https://docs.checkr.confluence/docs/ensure-that-the-admission-control-plugin-alwayspullimages-is-set",
    "CKV_K8S_81": "https://docs.checkr.confluence/docs/ensure-that-the-admission-control-plugin-securitycontextdeny-is-set-if-podsecuritypolicy-is-not-used",
    "CKV_K8S_82": "https://docs.checkr.confluence/docs/ensure-that-the-admission-control-plugin-serviceaccount-is-set",
    "CKV_K8S_83": "https://docs.checkr.confluence/docs/ensure-that-the-admission-control-plugin-namespacelifecycle-is-set",
    "CKV_K8S_84": "https://docs.checkr.confluence/docs/ensure-that-the-admission-control-plugin-podsecuritypolicy-is-set",
    "CKV_K8S_85": "https://docs.checkr.confluence/docs/ensure-that-the-admission-control-plugin-noderestriction-is-set",
    "CKV_K8S_86": "https://docs.checkr.confluence/docs/ensure-that-the-insecure-bind-address-argument-is-not-set",
    "CKV_K8S_88": "https://docs.checkr.confluence/docs/ensure-that-the-insecure-port-argument-is-set-to-0",
    "CKV_K8S_89": "https://docs.checkr.confluence/docs/ensure-that-the-secure-port-argument-is-not-set-to-0",
    "CKV_K8S_90": "https://docs.checkr.confluence/docs/ensure-that-the-profiling-argument-is-set-to-false-2",
    "CKV_K8S_91": "https://docs.checkr.confluence/docs/ensure-that-the-audit-log-path-argument-is-set",
    "CKV_K8S_92": "https://docs.checkr.confluence/docs/ensure-that-the-audit-log-maxage-argument-is-set-to-30-or-as-appropriate",
    "CKV_K8S_93": "https://docs.checkr.confluence/docs/ensure-that-the-audit-log-maxbackup-argument-is-set-to-10-or-as-appropriate",
    "CKV_K8S_94": "https://docs.checkr.confluence/docs/ensure-that-the-audit-log-maxsize-argument-is-set-to-100-or-as-appropriate",
    "CKV_K8S_95": "https://docs.checkr.confluence/docs/ensure-that-the-request-timeout-argument-is-set-as-appropriate",
    "CKV_K8S_96": "https://docs.checkr.confluence/docs/ensure-that-the-service-account-lookup-argument-is-set-to-true",
    "CKV_K8S_97": "https://docs.checkr.confluence/docs/ensure-that-the-service-account-key-file-argument-is-set-as-appropriate",
    "CKV_K8S_99": "https://docs.checkr.confluence/docs/ensure-that-the-etcd-certfile-and-etcd-keyfile-arguments-are-set-as-appropriate",
    "CKV_K8S_100": "https://docs.checkr.confluence/docs/ensure-that-the-tls-cert-file-and-tls-private-key-file-arguments-are-set-as-appropriate",
    "CKV_K8S_102": "https://docs.checkr.confluence/docs/ensure-that-the-etcd-cafile-argument-is-set-as-appropriate-1",
    "CKV_K8S_104": "https://docs.checkr.confluence/docs/ensure-that-the-etcd-cafile-argument-is-set-as-appropriate",
    "CKV_K8S_105": "https://docs.checkr.confluence/docs/ensure-that-the-api-server-only-makes-use-of-strong-cryptographic-ciphers",
    "CKV_K8S_106": "https://docs.checkr.confluence/docs/ensure-that-the-terminated-pod-gc-threshold-argument-is-set-as-appropriate",
    "CKV_K8S_107": "https://docs.checkr.confluence/docs/ensure-that-the-profiling-argument-is-set-to-false",
    "CKV_K8S_108": "https://docs.checkr.confluence/docs/ensure-that-the-use-service-account-credentials-argument-is-set-to-true",
    "CKV_K8S_110": "https://docs.checkr.confluence/docs/ensure-that-the-service-account-private-key-file-argument-is-set-as-appropriate",
    "CKV_K8S_111": "https://docs.checkr.confluence/docs/ensure-that-the-root-ca-file-argument-is-set-as-appropriate",
    "CKV_K8S_112": "https://docs.checkr.confluence/docs/ensure-that-the-rotatekubeletservercertificate-argument-is-set-to-true-for-controller-manager",
    "CKV_K8S_113": "https://docs.checkr.confluence/docs/ensure-that-the-bind-address-argument-is-set-to-127001",
    "CKV_K8S_114": "https://docs.checkr.confluence/docs/ensure-that-the-profiling-argument-is-set-to-false-1",
    "CKV_K8S_115": "https://docs.checkr.confluence/docs/ensure-that-the-bind-address-argument-is-set-to-127001-1",
    "CKV_K8S_116": "https://docs.checkr.confluence/docs/ensure-that-the-cert-file-and-key-file-arguments-are-set-as-appropriate",
    "CKV_K8S_117": "https://docs.checkr.confluence/docs/ensure-that-the-client-cert-auth-argument-is-set-to-true",
    "CKV_K8S_118": "https://docs.checkr.confluence/docs/ensure-that-the-auto-tls-argument-is-not-set-to-true",
    "CKV_K8S_119": "https://docs.checkr.confluence/docs/ensure-that-the-peer-cert-file-and-peer-key-file-arguments-are-set-as-appropriate",
    "CKV_K8S_121": "https://docs.checkr.confluence/docs/ensure-that-the-peer-client-cert-auth-argument-is-set-to-true",
    "CKV_K8S_138": "https://docs.checkr.confluence/docs/ensure-that-the-anonymous-auth-argument-is-set-to-false",
    "CKV_K8S_139": "https://docs.checkr.confluence/docs/ensure-that-the-authorization-mode-argument-is-not-set-to-alwaysallow",
    "CKV_K8S_140": "https://docs.checkr.confluence/docs/ensure-that-the-client-ca-file-argument-is-set-as-appropriate-scored",
    "CKV_K8S_141": "https://docs.checkr.confluence/docs/ensure-that-the-read-only-port-argument-is-set-to-0",
    "CKV_K8S_143": "https://docs.checkr.confluence/docs/ensure-that-the-streaming-connection-idle-timeout-argument-is-not-set-to-0",
    "CKV_K8S_144": "https://docs.checkr.confluence/docs/ensure-that-the-protect-kernel-defaults-argument-is-set-to-true",
    "CKV_K8S_145": "https://docs.checkr.confluence/docs/ensure-that-the-make-iptables-util-chains-argument-is-set-to-true",
    "CKV_K8S_146": "https://docs.checkr.confluence/docs/ensure-that-the-hostname-override-argument-is-not-set",
    "CKV_K8S_147": "https://docs.checkr.confluence/docs/ensure-that-the-event-qps-argument-is-set-to-0-or-a-level-which-ensures-appropriate-event-capture",
    "CKV_K8S_148": "https://docs.checkr.confluence/docs/ensure-that-the-tls-cert-file-and-tls-private-key-file-arguments-are-set-as-appropriate-for-kubelet",
    "CKV_K8S_149": "https://docs.checkr.confluence/docs/ensure-that-the-rotate-certificates-argument-is-not-set-to-false",
    "CKV_K8S_151": "https://docs.checkr.confluence/docs/ensure-that-the-kubelet-only-makes-use-of-strong-cryptographic-ciphers",
    "CKV_DOCKER_1": "https://docs.checkr.confluence/docs/ensure-port-22-is-not-exposed",
    "CKV_DOCKER_2": "https://docs.checkr.confluence/docs/ensure-that-healthcheck-instructions-have-been-added-to-container-images",
    "CKV_DOCKER_3": "https://docs.checkr.confluence/docs/ensure-that-a-user-for-the-container-has-been-created",
    "CKV_DOCKER_4": "https://docs.checkr.confluence/docs/ensure-that-copy-is-used-instead-of-add-in-dockerfiles",
    "CKV_DOCKER_5": "https://docs.checkr.confluence/docs/ensure-update-instructions-are-not-used-alone-in-the-dockerfile",
    "CKV_SECRET_1": "https://docs.checkr.confluence/docs/git_secrets_1",
    "CKV_SECRET_2": "https://docs.checkr.confluence/docs/git_secrets_2",
    "CKV_SECRET_3": "https://docs.checkr.confluence/docs/git_secrets_3",
    "CKV_SECRET_4": "https://docs.checkr.confluence/docs/git_secrets_4",
    "CKV_SECRET_5": "https://docs.checkr.confluence/docs/git_secrets_5",
    "CKV_SECRET_8": "https://docs.checkr.confluence/docs/git_secrets_8",
    "CKV_SECRET_9": "https://docs.checkr.confluence/docs/git_secrets_9",
    "CKV_SECRET_10": "https://docs.checkr.confluence/docs/git_secrets_10",
    "CKV_SECRET_11": "https://docs.checkr.confluence/docs/git_secrets_11",
    "CKV_SECRET_12": "https://docs.checkr.confluence/docs/git_secrets_12",
    "CKV_SECRET_13": "https://docs.checkr.confluence/docs/git_secrets_13",
    "CKV_SECRET_14": "https://docs.checkr.confluence/docs/git_secrets_14",
    "CKV_SECRET_15": "https://docs.checkr.confluence/docs/git_secrets_15",
    "CKV_SECRET_16": "https://docs.checkr.confluence/docs/git_secrets_16",
    "CKV_SECRET_17": "https://docs.checkr.confluence/docs/git_secrets_17",
    "CKV_SECRET_18": "https://docs.checkr.confluence/docs/git_secrets_18",
    "CKV_SECRET_19": "https://docs.checkr.confluence/docs/git_secrets_19"
  },
  "idMapping": {
    "BC_GIT_6": "CKV_SECRET_6",
    "BC_AWS_IAM_6": "CKV_AWS_11",
    "BC_AWS_IAM_8": "CKV_AWS_12",
    "BC_AWS_IAM_16": "CKV_AWS_40",
    "BC_GIT_7": "CKV_SECRET_7",
    "BC_AWS_IAM_7": "CKV_AWS_14",
    "BC_AWS_IAM_43": "CKV_AWS_49",
    "BC_AWS_IAM_44": "CKV_AWS_60",
    "BC_AWS_IAM_45": "CKV_AWS_61",
    "BC_AWS_IAM_46": "CKV_AWS_72",
    "BC_AWS_LOGGING_1": "CKV_AWS_67",
    "BC_AWS_LOGGING_2": "CKV_AWS_36",
    "BC_AWS_LOGGING_11": "CKV_AWS_65",
    "BC_AWS_NETWORKING_1": "CKV_AWS_24",
    "BC_AWS_NETWORKING_2": "CKV_AWS_25",
    "BC_AWS_NETWORKING_4": "CKV2_AWS_12",
    "BC_AWS_NETWORKING_29": "CKV_AWS_2",
    "BC_AWS_NETWORKING_31": "CKV_AWS_23",
    "BC_AWS_NETWORKING_32": "CKV_AWS_34",
    "BC_AWS_KUBERNETES_1": "CKV_AWS_38",
    "BC_AWS_IAM_9": "CKV_AWS_10",
    "BC_AWS_KUBERNETES_2": "CKV_AWS_39",
    "BC_AWS_KUBERNETES_3": "CKV_AWS_58",
    "BC_AWS_KUBERNETES_4": "CKV_AWS_37",
    "BC_AWS_SERVERLESS_4": "CKV_AWS_50",
    "BC_AWS_GENERAL_3": "CKV_AWS_3",
    "BC_AWS_GENERAL_4": "CKV_AWS_16",
    "BC_AWS_GENERAL_6": "CKV_AWS_28",
    "BC_AWS_GENERAL_7": "CKV_AWS_4",
    "BC_AWS_GENERAL_8": "CKV_AWS_163",
    "BC_AWS_GENERAL_9": "CKV_AWS_29",
    "BC_AWS_GENERAL_10": "CKV_AWS_30",
    "BC_AWS_GENERAL_11": "CKV_AWS_31",
    "BC_AWS_GENERAL_13": "CKV_AWS_8",
    "BC_AWS_GENERAL_14": "CKV_AWS_22",
    "BC_AWS_GENERAL_15": "CKV_AWS_26",
    "BC_AWS_GENERAL_16": "CKV_AWS_27",
    "BC_AWS_GENERAL_17": "CKV_AWS_42",
    "BC_AWS_GENERAL_18": "CKV_AWS_44",
    "BC_AWS_GENERAL_22": "CKV_AWS_43",
    "BC_AWS_GENERAL_23": "CKV_AWS_47",
    "BC_AWS_GENERAL_24": "CKV_AWS_51",
    "BC_AWS_GENERAL_25": "CKV_AWS_64",
    "BC_AWS_LOGGING_12": "CKV_AWS_71",
    "BC_AWS_GENERAL_26": "CKV_AWS_CUSTOM_1",
    "BC_AWS_ELASTICSEARCH_3": "CKV_AWS_5",
    "BC_AWS_ELASTICSEARCH_5": "CKV_AWS_6",
    "BC_AWS_ELASTICSEARCH_6": "CKV_AWS_83",
    "BC_AWS_S3_1": "CKV_AWS_20",
    "BC_AWS_S3_2": "CKV_AWS_57",
    "BC_AWS_S3_13": "CKV_AWS_18",
    "BC_AWS_S3_14": "CKV_AWS_19",
    "BC_AWS_S3_16": "CKV_AWS_21",
    "BC_AWS_S3_19": "CKV_AWS_53",
    "BC_AWS_S3_20": "CKV_AWS_54",
    "BC_AWS_S3_21": "CKV_AWS_55",
    "BC_AWS_S3_22": "CKV_AWS_56",
    "BC_AWS_S3_23": "CKV_AWS_70",
    "BC_AWS_SECRETS_1": "CKV_AWS_46",
    "BC_AWS_SECRETS_3": "CKV_AWS_45",
    "BC_AWS_SECRETS_5": "CKV_AWS_41",
    "BC_AWS_PUBLIC_1": "CKV_AWS_32",
    "BC_AWS_PUBLIC_2": "CKV_AWS_17",
    "BC_AWS_PUBLIC_6": "CKV_AWS_59",
    "BC_AWS_PUBLIC_9": "CKV_AWS_87",
    "BC_K8S_1": "CKV_K8S_1",
    "BC_K8S_2": "CKV_K8S_2",
    "BC_K8S_3": "CKV_K8S_3",
    "BC_K8S_4": "CKV_K8S_4",
    "BC_K8S_5": "CKV_K8S_6",
    "BC_K8S_6": "CKV_K8S_7",
    "BC_K8S_7": "CKV_K8S_8",
    "BC_K8S_8": "CKV_K8S_9",
    "BC_K8S_9": "CKV_K8S_10",
    "BC_K8S_10": "CKV_K8S_11",
    "BC_K8S_11": "CKV_K8S_12",
    "BC_K8S_12": "CKV_K8S_13",
    "BC_K8S_13": "CKV_K8S_14",
    "BC_K8S_14": "CKV_K8S_15",
    "BC_K8S_15": "CKV_K8S_16",
    "BC_K8S_16": "CKV_K8S_17",
    "BC_K8S_17": "CKV_K8S_18",
    "BC_K8S_18": "CKV_K8S_19",
    "BC_K8S_19": "CKV_K8S_20",
    "BC_K8S_20": "CKV_K8S_21",
    "BC_K8S_21": "CKV_K8S_22",
    "BC_K8S_22": "CKV_K8S_23",
    "BC_K8S_23": "CKV_K8S_24",
    "BC_K8S_24": "CKV_K8S_25",
    "BC_K8S_25": "CKV_K8S_26",
    "BC_K8S_26": "CKV_K8S_27",
    "BC_K8S_27": "CKV_K8S_28",
    "BC_K8S_28": "CKV_K8S_30",
    "BC_K8S_29": "CKV_K8S_31",
    "BC_K8S_30": "CKV_K8S_32",
    "BC_K8S_31": "CKV_K8S_33",
    "BC_K8S_32": "CKV_K8S_34",
    "BC_K8S_33": "CKV_K8S_35",
    "BC_K8S_34": "CKV_K8S_37",
    "BC_K8S_35": "CKV_K8S_38",
    "BC_K8S_37": "CKV_K8S_40",
    "BC_K8S_38": "CKV_K8S_41",
    "BC_K8S_39": "CKV_K8S_43",
    "BC_K8S_40": "CKV_K8S_45",
    "BC_K8S_41": "CKV_K8S_44",
    "BC_GCP_KUBERNETES_1": "CKV_GCP_1",
    "BC_GCP_KUBERNETES_2": "CKV_GCP_7",
    "BC_GCP_KUBERNETES_3": "CKV_GCP_8",
    "BC_GCP_KUBERNETES_4": "CKV_GCP_9",
    "BC_GCP_KUBERNETES_5": "CKV_GCP_10",
    "BC_GCP_KUBERNETES_6": "CKV_GCP_25",
    "BC_GCP_KUBERNETES_7": "CKV_GCP_12",
    "BC_GCP_KUBERNETES_8": "CKV_GCP_13",
    "BC_GCP_KUBERNETES_9": "CKV_GCP_24",
    "BC_GCP_KUBERNETES_10": "CKV_GCP_18",
    "BC_GCP_KUBERNETES_11": "CKV_GCP_19",
    "BC_GCP_KUBERNETES_12": "CKV_GCP_20",
    "BC_GCP_KUBERNETES_13": "CKV_GCP_21",
    "BC_GCP_KUBERNETES_14": "CKV_GCP_22",
    "BC_GCP_KUBERNETES_15": "CKV_GCP_23",
    "BC_GCP_NETWORKING_1": "CKV_GCP_2",
    "BC_GCP_NETWORKING_2": "CKV_GCP_3",
    "BC_GCP_NETWORKING_3": "CKV_GCP_4",
    "BC_GCP_NETWORKING_4": "CKV_GCP_11",
    "BC_GCP_NETWORKING_5": "CKV_GCP_16",
    "BC_GCP_NETWORKING_6": "CKV_GCP_17",
    "BC_GCP_NETWORKING_7": "CKV_GCP_27",
    "BC_GCP_NETWORKING_8": "CKV_GCP_32",
    "BC_GCP_NETWORKING_9": "CKV_GCP_33",
    "BC_GCP_NETWORKING_10": "CKV_GCP_34",
    "BC_GCP_NETWORKING_11": "CKV_GCP_35",
    "BC_GCP_NETWORKING_12": "CKV_GCP_36",
    "BC_GCP_GENERAL_1": "CKV_GCP_37",
    "BC_GCP_GENERAL_2": "CKV_GCP_38",
    "BC_GCP_GENERAL_3": "CKV_GCP_39",
    "BC_GCP_GENERAL_4": "CKV_GCP_43",
    "BC_GCP_GENERAL_5": "CKV_GCP_6",
    "BC_GCP_GENERAL_6": "CKV_GCP_14",
    "BC_GCP_GENERAL_7": "CKV_GCP_15",
    "BC_GCP_PUBLIC_1": "CKV_GCP_28",
    "BC_GCP_PUBLIC_2": "CKV_GCP_40",
    "BC_GCP_IAM_1": "CKV_GCP_30",
    "BC_GCP_IAM_2": "CKV_GCP_31",
    "BC_GCP_IAM_3": "CKV_GCP_41",
    "BC_GCP_IAM_4": "CKV_GCP_42",
    "BC_GCP_LOGGING_1": "CKV_GCP_26",
    "BC_GCP_GCS_1": "CKV_GCP_5",
    "BC_GCP_GCS_2": "CKV_GCP_29",
    "BC_AZR_NETWORKING_1": "CKV_AZURE_1",
    "BC_AZR_NETWORKING_2": "CKV_AZURE_9",
    "BC_AZR_NETWORKING_3": "CKV_AZURE_10",
    "BC_AZR_NETWORKING_4": "CKV_AZURE_11",
    "BC_AZR_NETWORKING_5": "CKV_AZURE_14",
    "BC_AZR_NETWORKING_7": "CKV_AZURE_17",
    "BC_AZR_NETWORKING_8": "CKV_AZURE_18",
    "BC_AZR_NETWORKING_9": "CKV_AZURE_28",
    "BC_AZR_NETWORKING_10": "CKV_AZURE_29",
    "BC_AZR_NETWORKING_11": "CKV_AZURE_30",
    "BC_AZR_NETWORKING_12": "CKV_AZURE_31",
    "BC_AZR_NETWORKING_13": "CKV_AZURE_32",
    "BC_AZR_NETWORKING_14": "CKV_AZURE_34",
    "BC_AZR_NETWORKING_15": "CKV_AZURE_35",
    "BC_AZR_NETWORKING_16": "CKV_AZURE_36",
    "BC_AZR_LOGGING_1": "CKV_AZURE_12",
    "BC_AZR_LOGGING_2": "CKV_AZURE_23",
    "BC_AZR_LOGGING_3": "CKV_AZURE_24",
    "BC_AZR_LOGGING_4": "CKV_AZURE_33",
    "BC_AZR_LOGGING_5": "CKV_AZURE_37",
    "BC_AZR_LOGGING_6": "CKV_AZURE_38",
    "BC_AZR_GENERAL_1": "CKV_AZURE_2",
    "BC_AZR_GENERAL_2": "CKV_AZURE_13",
    "BC_AZR_GENERAL_3": "CKV_AZURE_20",
    "BC_AZR_GENERAL_4": "CKV_AZURE_21",
    "BC_AZR_GENERAL_5": "CKV_AZURE_22",
    "BC_AZR_GENERAL_6": "CKV_AZURE_25",
    "BC_AZR_GENERAL_7": "CKV_AZURE_26",
    "BC_AZR_GENERAL_8": "CKV_AZURE_27",
    "BC_AZR_GENERAL_9": "CKV_AZURE_19",
    "BC_AZR_GENERAL_10": "CKV_AZURE_40",
    "BC_AZR_GENERAL_11": "CKV_AZURE_42",
    "BC_AZR_IAM_1": "CKV_AZURE_16",
    "BC_AZR_IAM_2": "CKV_AZURE_39",
    "BC_AZR_STORAGE_1": "CKV_AZURE_3",
    "BC_AZR_SECRETS_1": "CKV_AZURE_41",
    "BC_AZR_SECRETS_2": "CKV_AZURE_45",
    "BC_AZR_KUBERNETES_1": "CKV_AZURE_4",
    "BC_AZR_KUBERNETES_2": "CKV_AZURE_5",
    "BC_AZR_KUBERNETES_3": "CKV_AZURE_6",
    "BC_AZR_KUBERNETES_4": "CKV_AZURE_7",
    "BC_AZR_KUBERNETES_5": "CKV_AZURE_8",
    "BC_AWS_IAM_47": "CKV_AWS_62",
    "BC_AWS_IAM_48": "CKV_AWS_63",
    "BC_AWS_LOGGING_13": "CKV_AWS_66",
    "BC_AWS_GENERAL_27": "CKV_AWS_68",
    "BC_AWS_PUBLIC_11": "CKV_AWS_69",
    "BC_AWS_LOGGING_15": "CKV_AWS_73",
    "BC_AWS_GENERAL_28": "CKV_AWS_74",
    "BC_AWS_GENERAL_51": "CKV_AWS_132",
    "BC_AWS_LOGGING_16": "CKV_AWS_75",
    "BC_AWS_LOGGING_17": "CKV_AWS_76",
    "BC_AWS_GENERAL_30": "CKV_AWS_78",
    "BC_AWS_GENERAL_31": "CKV_AWS_79",
    "BC_AWS_LOGGING_18": "CKV_AWS_80",
    "BC_AWS_GENERAL_32": "CKV_AWS_81",
    "BC_AWS_GENERAL_33": "CKV_AWS_82",
    "BC_AWS_ELASTICSEARCH_7": "CKV_AWS_84",
    "BC_AWS_LOGGING_19": "CKV_AWS_85",
    "BC_AWS_LOGGING_20": "CKV_AWS_86",
    "BC_AWS_LOGGING_21": "CKV_AWS_CUSTOM_2",
    "BC_AZR_STORAGE_2": "CKV_AZURE_44",
    "BC_GCP_IAM_5": "CKV_GCP_44",
    "BC_GCP_IAM_6": "CKV_GCP_45",
    "BC_GCP_IAM_7": "CKV_GCP_46",
    "BC_GCP_IAM_8": "CKV_GCP_47",
    "BC_GCP_IAM_9": "CKV_GCP_48",
    "BC_GCP_IAM_10": "CKV_GCP_49",
    "BC_GCP_SQL_1": "CKV_GCP_50",
    "BC_GCP_SQL_2": "CKV_GCP_51",
    "BC_GCP_SQL_3": "CKV_GCP_52",
    "BC_GCP_SQL_4": "CKV_GCP_53",
    "BC_GCP_SQL_5": "CKV_GCP_54",
    "BC_GCP_SQL_6": "CKV_GCP_55",
    "BC_GCP_SQL_7": "CKV_GCP_56",
    "BC_GCP_SQL_8": "CKV_GCP_57",
    "BC_GCP_SQL_9": "CKV_GCP_58",
    "BC_GCP_SQL_10": "CKV_GCP_59",
    "BC_GCP_SQL_11": "CKV_GCP_60",
    "BC_K8S_42": "CKV_K8S_5",
    "BC_K8S_43": "CKV_K8S_29",
    "BC_K8S_44": "CKV_K8S_36",
    "BC_K8S_45": "CKV_K8S_42",
    "BC_AWS_PUBLIC_12": "CKV_AWS_88",
    "BC_AWS_PUBLIC_13": "CKV_AWS_89",
    "BC_AWS_NETWORKING_37": "CKV_AWS_90",
    "BC_AWS_LOGGING_22": "CKV_AWS_91",
    "BC_AWS_LOGGING_23": "CKV_AWS_92",
    "BC_AWS_S3_24": "CKV_AWS_93",
    "BC_AWS_GENERAL_37": "CKV_AWS_94",
    "BC_AWS_GENERAL_38": "CKV_AWS_96",
    "BC_AWS_GENERAL_39": "CKV_AWS_97",
    "BC_AWS_GENERAL_40": "CKV_AWS_98",
    "BC_AWS_GENERAL_41": "CKV_AWS_99",
    "BC_AWS_KUBERNETES_5": "CKV_AWS_100",
    "BC_AWS_LOGGING_24": "CKV_AWS_101",
    "BC_AWS_GENERAL_42": "CKV_AWS_102",
    "BC_AWS_GENERAL_43": "CKV_AWS_103",
    "BC_AZR_GENERAL_12": "CKV_AZURE_46",
    "BC_AZR_NETWORKING_17": "CKV_AZURE_47",
    "BC_AZR_PUBLIC_1": "CKV_AZURE_48",
    "BC_AZR_GENERAL_13": "CKV_AZURE_49",
    "BC_GCP_GCS_3": "CKV_GCP_62",
    "BC_AZR_GENERAL_14": "CKV_AZURE_50",
    "BC_GCP_GCS_4": "CKV_GCP_63",
    "BC_AWS_KUBERNETES_6": "CKV_AWS_106",
    "BC_AWS_IAM_54": "CKV_AWS_107",
    "BC_AWS_IAM_55": "CKV_AWS_108",
    "BC_AWS_IAM_56": "CKV_AWS_109",
    "BC_AWS_IAM_57": "CKV_AWS_111",
    "BC_AWS_GENERAL_61": "CKV_AWS_113",
    "BC_AWS_GENERAL_62": "CKV_AWS_114",
    "BC_AWS_GENERAL_63": "CKV_AWS_115",
    "BC_AWS_GENERAL_64": "CKV_AWS_116",
    "BC_AWS_GENERAL_65": "CKV_AWS_117",
    "BC_AWS_LOGGING_28": "CKV_AWS_118",
    "BC_AWS_GENERAL_52": "CKV_AWS_119",
    "BC_AWS_GENERAL_44": "CKV2_AWS_16",
    "BC_AWS_NETWORKING_38": "CKV_AWS_122",
    "BC_AWS_NETWORKING_39": "CKV_AWS_123",
    "BC_AWS_LOGGING_25": "CKV_AWS_124",
    "BC_AWS_LOGGING_26": "CKV_AWS_126",
    "BC_AWS_GENERAL_67": "CKV_AWS_127",
    "BC_AWS_IAM_59": "CKV_AWS_128",
    "BC_AWS_IAM_60": "CKV_AWS_129",
    "BC_AWS_NETWORKING_41": "CKV_AWS_131",
    "BC_AWS_GENERAL_46": "CKV_AWS_133",
    "BC_AWS_GENERAL_45": "CKV_AWS_134",
    "BC_AWS_GENERAL_68": "CKV_AWS_135",
    "BC_AWS_GENERAL_53": "CKV_AWS_136",
    "BC_AWS_NETWORKING_42": "CKV_AWS_137",
    "BC_AWS_NETWORKING_43": "CKV_AWS_138",
    "BC_AWS_GENERAL_69": "CKV_AWS_139",
    "BC_AWS_GENERAL_54": "CKV_AWS_140",
    "BC_AWS_GENERAL_70": "CKV_AWS_141",
    "BC_AWS_GENERAL_55": "CKV_AWS_142",
    "BC_AWS_GENERAL_71": "CKV_AWS_143",
    "BC_AWS_GENERAL_72": "CKV_AWS_144",
    "BC_AWS_GENERAL_73": "CKV_AWS_157",
    "BC_AWS_IAM_10": "CKV_AWS_13",
    "BC_AWS_GENERAL_56": "CKV_AWS_145",
    "BC_AWS_NETWORKING_50": "CKV2_AWS_1",
    "BC_AWS_GENERAL_60": "CKV2_AWS_2",
    "BC_AWS_GENERAL_66": "CKV2_AWS_3",
    "BC_AWS_LOGGING_29": "CKV2_AWS_4",
    "BC_AWS_NETWORKING_51": "CKV2_AWS_5",
    "BC_AWS_NETWORKING_52": "CKV2_AWS_6",
    "BC_AWS_NETWORKING_40": "CKV2_AWS_7",
    "BC_AWS_GENERAL_49": "CKV2_AWS_8",
    "BC_AWS_GENERAL_50": "CKV2_AWS_9",
    "BC_AWS_LOGGING_27": "CKV2_AWS_10",
    "BC_AWS_GENERAL_47": "CKV2_AWS_13",
    "BC_AWS_IAM_61": "CKV2_AWS_14",
    "BC_AWS_NETWORKING_46": "CKV2_AWS_15",
    "BC_AWS_NETWORKING_47": "CKV2_AWS_17",
    "BC_AWS_GENERAL_48": "CKV2_AWS_18",
    "BC_AWS_NETWORKING_48": "CKV2_AWS_19",
    "BC_AWS_NETWORKING_49": "CKV2_AWS_20",
    "BC_AWS_IAM_62": "CKV2_AWS_21",
    "BC_AZR_GENERAL_46": "CKV_AZURE_55",
    "BC_AZR_GENERAL_47": "CKV_AZURE_56",
    "BC_AZR_GENERAL_48": "CKV_AZURE_57",
    "BC_AZR_NETWORKING_43": "CKV_AZURE_58",
    "BC_AZR_NETWORKING_18": "CKV_AZURE_59",
    "BC_AZR_NETWORKING_19": "CKV_AZURE_60",
    "BC_AZR_GENERAL_50": "CKV_AZURE_61",
    "BC_AZR_GENERAL_51": "CKV_AZURE_62",
    "BC_AZR_LOGGING_8": "CKV_AZURE_63",
    "BC_AZR_NETWORKING_42": "CKV_AZURE_64",
    "BC_AZR_LOGGING_9": "CKV_AZURE_65",
    "BC_AZR_LOGGING_10": "CKV_AZURE_66",
    "BC_AZR_GENERAL_52": "CKV_AZURE_67",
    "BC_AZR_NETWORKING_20": "CKV_AZURE_68",
    "BC_AZR_GENERAL_53": "CKV_AZURE_69",
    "BC_AZR_NETWORKING_21": "CKV_AZURE_70",
    "BC_AZR_GENERAL_54": "CKV_AZURE_71",
    "BC_AZR_GENERAL_55": "CKV_AZURE_72",
    "BC_AZR_GENERAL_25": "CKV_AZURE_73",
    "BC_AZR_GENERAL_26": "CKV_AZURE_74",
    "BC_AZR_GENERAL_27": "CKV_AZURE_75",
    "BC_AZR_GENERAL_28": "CKV_AZURE_76",
    "BC_AZR_NETWORKING_22": "CKV_AZURE_77",
    "BC_AZR_GENERAL_15": "CKV_AZURE_78",
    "BC_AZR_GENERAL_56": "CKV_AZURE_79",
    "BC_AZR_GENERAL_57": "CKV_AZURE_80",
    "BC_AZR_GENERAL_58": "CKV_AZURE_81",
    "BC_AZR_GENERAL_59": "CKV_AZURE_82",
    "BC_AZR_GENERAL_60": "CKV_AZURE_83",
    "BC_AZR_GENERAL_61": "CKV_AZURE_84",
    "BC_AZR_GENERAL_62": "CKV_AZURE_85",
    "BC_AZR_GENERAL_63": "CKV_AZURE_86",
    "BC_AZR_GENERAL_64": "CKV_AZURE_87",
    "BC_AZR_GENERAL_65": "CKV_AZURE_88",
    "BC_AZR_NETWORKING_23": "CKV_AZURE_89",
    "BC_AZR_NETWORKING_44": "CKV_AZURE_90",
    "BC_AZR_NETWORKING_24": "CKV_AZURE_91",
    "BC_AZR_GENERAL_66": "CKV_AZURE_92",
    "BC_AZR_GENERAL_29": "CKV_AZURE_93",
    "BC_AZR_GENERAL_19": "CKV_AZURE_94",
    "BC_AZR_GENERAL_67": "CKV_AZURE_95",
    "BC_AZR_GENERAL_30": "CKV_AZURE_96",
    "BC_AZR_GENERAL_31": "CKV_AZURE_97",
    "BC_AZR_NETWORKING_25": "CKV_AZURE_98",
    "BC_AZR_NETWORKING_26": "CKV_AZURE_99",
    "BC_AZR_GENERAL_21": "CKV_AZURE_100",
    "BC_AZR_NETWORKING_28": "CKV_AZURE_101",
    "BC_AZR_GENERAL_16": "CKV_AZURE_102",
    "BC_AZR_GENERAL_39": "CKV_AZURE_103",
    "BC_AZR_NETWORKING_29": "CKV_AZURE_104",
    "BC_AWS_IAM_11": "CKV_AWS_9",
    "BC_AZR_GENERAL_22": "CKV_AZURE_105",
    "BC_AZR_NETWORKING_30": "CKV_AZURE_106",
    "BC_AZR_NETWORKING_31": "CKV_AZURE_107",
    "BC_AZR_NETWORKING_32": "CKV_AZURE_108",
    "BC_AZR_NETWORKING_33": "CKV_AZURE_109",
    "BC_AZR_GENERAL_40": "CKV_AZURE_110",
    "BC_AZR_GENERAL_41": "CKV_AZURE_111",
    "BC_AZR_GENERAL_17": "CKV_AZURE_112",
    "BC_AZR_NETWORKING_34": "CKV_AZURE_113",
    "BC_AZR_GENERAL_42": "CKV_AZURE_114",
    "BC_AZR_KUBERNETES_6": "CKV_AZURE_115",
    "BC_AZR_KUBERNETES_7": "CKV_AZURE_116",
    "BC_AZR_KUBERNETES_8": "CKV_AZURE_117",
    "BC_AZR_NETWORKING_35": "CKV_AZURE_118",
    "BC_AZR_NETWORKING_36": "CKV_AZURE_119",
    "BC_AZR_NETWORKING_37": "CKV_AZURE_120",
    "BC_AZR_NETWORKING_38": "CKV_AZURE_121",
    "BC_AZR_NETWORKING_39": "CKV_AZURE_122",
    "BC_AZR_NETWORKING_40": "CKV_AZURE_123",
    "BC_AZR_NETWORKING_41": "CKV_AZURE_124",
    "BC_AZR_GENERAL_44": "CKV_AZURE_127",
    "BC_AZR_GENERAL_45": "CKV_AZURE_128",
    "BC_AZR_GENERAL_18": "CKV_AZURE_129",
    "BC_AZR_GENERAL_24": "CKV_AZURE_130",
    "BC_AZR_GENERAL_49": "CKV_AZURE_131",
    "BC_AZR_GENERAL_32": "CKV2_AZURE_1",
    "BC_AZR_GENERAL_70": "CKV2_AZURE_2",
    "BC_AZR_GENERAL_71": "CKV2_AZURE_3",
    "BC_AZR_GENERAL_72": "CKV2_AZURE_4",
    "BC_AZR_GENERAL_73": "CKV2_AZURE_5",
    "BC_AZR_GENERAL_74": "CKV2_AZURE_7",
    "BC_AZR_LOGGING_12": "CKV2_AZURE_8",
    "BC_AZR_GENERAL_75": "CKV2_AZURE_9",
    "BC_AZR_GENERAL_68": "CKV2_AZURE_10",
    "BC_AZR_GENERAL_33": "CKV2_AZURE_11",
    "BC_AZR_GENERAL_20": "CKV2_AZURE_12",
    "BC_AZR_GENERAL_69": "CKV2_AZURE_13",
    "BC_AZR_GENERAL_34": "CKV2_AZURE_14",
    "BC_AZR_GENERAL_35": "CKV2_AZURE_15",
    "BC_AZR_GENERAL_36": "CKV2_AZURE_16",
    "BC_AZR_GENERAL_37": "CKV2_AZURE_17",
    "BC_AZR_GENERAL_38": "CKV2_AZURE_18",
    "BC_AZR_NETWORKING_27": "CKV2_AZURE_19",
    "BC_AZR_LOGGING_7": "CKV2_AZURE_20",
    "BC_AZR_LOGGING_11": "CKV2_AZURE_21",
    "BC_GCP_KUBERNETES_18": "CKV_GCP_61",
    "BC_GCP_KUBERNETES_19": "CKV_GCP_64",
    "BC_GCP_KUBERNETES_20": "CKV_GCP_65",
    "BC_GCP_KUBERNETES_21": "CKV_GCP_66",
    "BC_GCP_KUBERNETES_22": "CKV_GCP_67",
    "BC_GCP_KUBERNETES_17": "CKV_GCP_68",
    "BC_GCP_KUBERNETES_23": "CKV_GCP_69",
    "BC_GCP_KUBERNETES_24": "CKV_GCP_71",
    "BC_GCP_KUBERNETES_25": "CKV_GCP_72",
    "BC_GCP_KUBERNETES_16": "CKV2_GCP_1",
    "BC_GCP_NETWORKING_13": "CKV2_GCP_2",
    "BC_GCP_GENERAL_8": "CKV2_GCP_3",
    "BC_GCP_LOGGING_4": "CKV2_GCP_4",
    "BC_GCP_LOGGING_5": "CKV2_GCP_5",
    "BC_GCP_GENERAL_9": "CKV2_GCP_6",
    "BC_GCP_IAM_11": "CKV2_GCP_7",
    "BC_K8S_46": "CKV_K8S_68",
    "BC_K8S_47": "CKV_K8S_69",
    "BC_K8S_48": "CKV_K8S_70",
    "BC_K8S_49": "CKV_K8S_71",
    "BC_K8S_50": "CKV_K8S_72",
    "BC_K8S_51": "CKV_K8S_73",
    "BC_K8S_52": "CKV_K8S_74",
    "BC_K8S_56": "CKV_K8S_79",
    "BC_AWS_IAM_5": "CKV_AWS_15",
    "BC_AWS_IAM_23": "CKV_AWS_1",
    "BC_AWS_LOGGING_5": "CKV_AWS_121",
    "BC_AWS_LOGGING_7": "CKV_AWS_35",
    "BC_AWS_LOGGING_8": "CKV_AWS_7",
    "BC_AWS_LOGGING_9": "CKV2_AWS_11",
    "BC_AWS_LOGGING_10": "CKV_AWS_48",
    "BC_K8S_36": "CKV_K8S_39",
    "BC_AZR_NETWORKING_6": "CKV_AZURE_15",
    "BC_AWS_GENERAL_29": "CKV_AWS_77",
    "BC_K8S_53": "CKV_K8S_75",
    "BC_K8S_54": "CKV_K8S_77",
    "BC_K8S_55": "CKV_K8S_78",
    "BC_K8S_57": "CKV_K8S_80",
    "BC_K8S_58": "CKV_K8S_81",
    "BC_K8S_59": "CKV_K8S_82",
    "BC_K8S_60": "CKV_K8S_83",
    "BC_K8S_61": "CKV_K8S_84",
    "BC_K8S_62": "CKV_K8S_85",
    "BC_K8S_63": "CKV_K8S_86",
    "BC_K8S_64": "CKV_K8S_88",
    "BC_K8S_65": "CKV_K8S_89",
    "BC_K8S_66": "CKV_K8S_90",
    "BC_K8S_67": "CKV_K8S_91",
    "BC_K8S_68": "CKV_K8S_92",
    "BC_K8S_69": "CKV_K8S_93",
    "BC_K8S_70": "CKV_K8S_94",
    "BC_K8S_71": "CKV_K8S_95",
    "BC_K8S_72": "CKV_K8S_96",
    "BC_K8S_73": "CKV_K8S_97",
    "BC_K8S_74": "CKV_K8S_99",
    "BC_K8S_75": "CKV_K8S_100",
    "BC_K8S_77": "CKV_K8S_102",
    "BC_K8S_78": "CKV_K8S_104",
    "BC_K8S_79": "CKV_K8S_105",
    "BC_K8S_80": "CKV_K8S_106",
    "BC_K8S_81": "CKV_K8S_107",
    "BC_K8S_82": "CKV_K8S_108",
    "BC_K8S_83": "CKV_K8S_110",
    "BC_K8S_84": "CKV_K8S_111",
    "BC_K8S_85": "CKV_K8S_112",
    "BC_K8S_86": "CKV_K8S_113",
    "BC_K8S_87": "CKV_K8S_114",
    "BC_K8S_88": "CKV_K8S_115",
    "BC_K8S_89": "CKV_K8S_116",
    "BC_K8S_90": "CKV_K8S_117",
    "BC_K8S_91": "CKV_K8S_118",
    "BC_K8S_92": "CKV_K8S_119",
    "BC_K8S_93": "CKV_K8S_121",
    "BC_K8S_95": "CKV_K8S_138",
    "BC_K8S_96": "CKV_K8S_139",
    "BC_K8S_97": "CKV_K8S_140",
    "BC_K8S_98": "CKV_K8S_141",
    "BC_K8S_99": "CKV_K8S_143",
    "BC_K8S_100": "CKV_K8S_144",
    "BC_K8S_101": "CKV_K8S_145",
    "BC_K8S_102": "CKV_K8S_146",
    "BC_K8S_103": "CKV_K8S_147",
    "BC_K8S_104": "CKV_K8S_148",
    "BC_K8S_105": "CKV_K8S_149",
    "BC_K8S_76": "CKV_K8S_151",
    "BC_DKR_1": "CKV_DOCKER_1",
    "BC_DKR_2": "CKV_DOCKER_2",
    "BC_DKR_3": "CKV_DOCKER_3",
    "BC_DKR_5": "CKV_DOCKER_4",
    "BC_DKR_4": "CKV_DOCKER_5",
    "BC_GIT_1": "CKV_SECRET_1",
    "BC_GIT_2": "CKV_SECRET_2",
    "BC_GIT_3": "CKV_SECRET_3",
    "BC_GIT_4": "CKV_SECRET_4",
    "BC_GIT_5": "CKV_SECRET_5",
    "BC_GIT_8": "CKV_SECRET_8",
    "BC_GIT_9": "CKV_SECRET_9",
    "BC_GIT_10": "CKV_SECRET_10",
    "BC_GIT_11": "CKV_SECRET_11",
    "BC_GIT_12": "CKV_SECRET_12",
    "BC_GIT_13": "CKV_SECRET_13",
    "BC_GIT_14": "CKV_SECRET_14",
    "BC_GIT_15": "CKV_SECRET_15",
    "BC_GIT_16": "CKV_SECRET_16",
    "BC_GIT_17": "CKV_SECRET_17",
    "BC_GIT_18": "CKV_SECRET_18",
    "BC_GIT_19": "CKV_SECRET_19"
  }
}